setup.py
azure_translator/__init__.py
azure_translator/errors.py
azure_translator.egg-info/PKG-INFO
azure_translator.egg-info/SOURCES.txt
azure_translator.egg-info/dependency_links.txt
azure_translator.egg-info/requires.txt
azure_translator.egg-info/top_level.txt