Metadata-Version: 1.1
Name: azure-translator
Version: 0.1.3
Summary: Python SDK for Azure Translator API.
Home-page: https://github.com/Work4Labs/azure-translator-python-sdk
Author: mvdb
Author-email: mvdb@work4labs.com
License: Apache
Platform: UNKNOWN
Classifier: Development Status :: 3 - Alpha
Classifier: Intended Audience :: Developers
Classifier: Topic :: Software Development :: Build Tools
Classifier: License :: OSI Approved :: Apache Software License
Classifier: Programming Language :: Python :: 2
Classifier: Programming Language :: Python :: 2.7
